{"classes":[{"name":"version","path":"d3","type":"String"},{"name":"ascending","path":"d3","type":"Function","args":["a","b"]},{"name":"descending","path":"d3","type":"Function","args":["a","b"]},{"name":"min","path":"d3","type":"Function","args":["array","f"]},{"name":"max","path":"d3","type":"Function","args":["array","f"]},{"name":"extent","path":"d3","type":"Function","args":["array","f"]},{"name":"sum","path":"d3","type":"Function","args":["array","f"]},{"name":"mean","path":"d3","type":"Function","args":["array","f"]},{"name":"quantile","path":"d3","type":"Function","args":["values","p"]},{"name":"median","path":"d3","type":"Function","args":["array","f"]},{"name":"variance","path":"d3","type":"Function","args":["array","f"]},{"name":"deviation","path":"d3","type":"Function"},{"name":"bisectLeft","path":"d3","type":"Function","args":["a","x","lo","hi"]},{"name":"bisectRight","path":"d3","type":"Function","args":["a","x","lo","hi"]},{"name":"bisect","path":"d3","type":"Function","args":["a","x","lo","hi"]},{"name":"bisector","path":"d3","type":"Function","args":["f"]},{"name":"shuffle","path":"d3","type":"Function","args":["array","i0","i1"]},{"name":"permute","path":"d3","type":"Function","args":["array","indexes"]},{"name":"pairs","path":"d3","type":"Function","args":["array"]},{"name":"transpose","path":"d3","type":"Function","args":["matrix"]},{"name":"zip","path":"d3","type":"Function"},{"name":"keys","path":"d3","type":"Function","args":["map"]},{"name":"values","path":"d3","type":"Function","args":["map"]},{"name":"entries","path":"d3","type":"Function","args":["map"]},{"name":"merge","path":"d3","type":"Function","args":["arrays"]},{"name":"range","path":"d3","type":"Function","args":["start","stop","step"]},{"name":"map","path":"d3","type":"Function","args":["object","f"]},{"name":"nest","path":"d3","type":"Function"},{"name":"set","path":"d3","type":"Function","args":["array"]},{"name":"drag","path":"d3.behavior","type":"Function"},{"name":"zoom","path":"d3.behavior","type":"Function"},{"name":"behavior","path":"d3","type":"Object"},{"name":"rebind","path":"d3","type":"Function","args":["target","source"]},{"name":"dispatch","path":"d3","type":"Function"},{"name":"requote","path":"d3","type":"Function","args":["s"]},{"name":"length","path":"d3.selection","type":"Number"},{"name":"select","path":"d3.selection","type":"Function","args":["selector"]},{"name":"selectAll","path":"d3.selection","type":"Function","args":["selector"]},{"name":"attr","path":"d3.selection","type":"Function","args":["name","value"]},{"name":"classed","path":"d3.selection","type":"Function","args":["name","value"]},{"name":"style","path":"d3.selection","type":"Function","args":["name","value","priority"]},{"name":"property","path":"d3.selection","type":"Function","args":["name","value"]},{"name":"text","path":"d3.selection","type":"Function","args":["value"]},{"name":"html","path":"d3.selection","type":"Function","args":["value"]},{"name":"append","path":"d3.selection","type":"Function","args":["name"]},{"name":"insert","path":"d3.selection","type":"Function","args":["name","before"]},{"name":"remove","path":"d3.selection","type":"Function"},{"name":"data","path":"d3.selection","type":"Function","args":["value","key"]},{"name":"datum","path":"d3.selection","type":"Function","args":["value"]},{"name":"filter","path":"d3.selection","type":"Function","args":["filter"]},{"name":"order","path":"d3.selection","type":"Function"},{"name":"sort","path":"d3.selection","type":"Function","args":["comparator"]},{"name":"each","path":"d3.selection","type":"Function","args":["callback"]},{"name":"call","path":"d3.selection","type":"Function","args":["callback"]},{"name":"empty","path":"d3.selection","type":"Function"},{"name":"node","path":"d3.selection","type":"Function"},{"name":"size","path":"d3.selection","type":"Function"},{"name":"on","path":"d3.selection","type":"Function","args":["type","listener","capture"]},{"name":"transition","path":"d3.selection","type":"Function","args":["name"]},{"name":"interrupt","path":"d3.selection","type":"Function","args":["name"]},{"name":"length","path":"d3.selection","type":"Number"},{"name":"selection","path":"d3","type":"Function"},{"name":"prefix","path":"d3.ns","type":"Object"},{"name":"qualify","path":"d3.ns","type":"Function","args":["name"]},{"name":"ns","path":"d3","type":"Object"},{"name":"select","path":"d3","type":"Function","args":["node"]},{"name":"selectAll","path":"d3","type":"Function","args":["nodes"]},{"name":"mouse","path":"d3","type":"Function","args":["container"]},{"name":"touch","path":"d3","type":"Function","args":["container","touches","identifier"]},{"name":"touches","path":"d3","type":"Function","args":["container","touches"]},{"name":"interpolateZoom","path":"d3","type":"Function","args":["p0","p1"]},{"name":"toString","path":"d3.color","type":"Function"},{"name":"color","path":"d3","type":"Function"},{"name":"brighter","path":"d3.hsl","type":"Function","args":["k"]},{"name":"darker","path":"d3.hsl","type":"Function","args":["k"]},{"name":"rgb","path":"d3.hsl","type":"Function"},{"name":"hsl","path":"d3","type":"Function","args":["h","s","l"]},{"name":"brighter","path":"d3.hcl","type":"Function","args":["k"]},{"name":"darker","path":"d3.hcl","type":"Function","args":["k"]},{"name":"rgb","path":"d3.hcl","type":"Function"},{"name":"hcl","path":"d3","type":"Function","args":["h","c","l"]},{"name":"brighter","path":"d3.lab","type":"Function","args":["k"]},{"name":"darker","path":"d3.lab","type":"Function","args":["k"]},{"name":"rgb","path":"d3.lab","type":"Function"},{"name":"lab","path":"d3","type":"Function","args":["l","a","b"]},{"name":"brighter","path":"d3.rgb","type":"Function","args":["k"]},{"name":"darker","path":"d3.rgb","type":"Function","args":["k"]},{"name":"hsl","path":"d3.rgb","type":"Function"},{"name":"toString","path":"d3.rgb","type":"Function"},{"name":"rgb","path":"d3","type":"Function","args":["r","g","b"]},{"name":"functor","path":"d3","type":"Function","args":["v"]},{"name":"xhr","path":"d3","type":"Function","args":["url","mimeType","callback"]},{"name":"dsv","path":"d3","type":"Function","args":["delimiter","mimeType"]},{"name":"csv","path":"d3","type":"Function","args":["url","row","callback"]},{"name":"tsv","path":"d3","type":"Function","args":["url","row","callback"]},{"name":"timer","path":"d3","type":"Function"},{"name":"round","path":"d3","type":"Function","args":["x","n"]},{"name":"formatPrefix","path":"d3","type":"Function","args":["value","precision"]},{"name":"year","path":"d3.time","type":"Function","args":["date"]},{"name":"years","path":"d3.time","type":"Function","args":["t0","t1","dt"]},{"name":"day","path":"d3.time","type":"Function","args":["date"]},{"name":"days","path":"d3.time","type":"Function","args":["t0","t1","dt"]},{"name":"dayOfYear","path":"d3.time","type":"Function","args":["date"]},{"name":"sunday","path":"d3.time","type":"Function","args":["date"]},{"name":"sundays","path":"d3.time","type":"Function","args":["t0","t1","dt"]},{"name":"sundayOfYear","path":"d3.time","type":"Function","args":["date"]},{"name":"monday","path":"d3.time","type":"Function","args":["date"]},{"name":"mondays","path":"d3.time","type":"Function","args":["t0","t1","dt"]},{"name":"mondayOfYear","path":"d3.time","type":"Function","args":["date"]},{"name":"tuesday","path":"d3.time","type":"Function","args":["date"]},{"name":"tuesdays","path":"d3.time","type":"Function","args":["t0","t1","dt"]},{"name":"tuesdayOfYear","path":"d3.time","type":"Function","args":["date"]},{"name":"wednesday","path":"d3.time","type":"Function","args":["date"]},{"name":"wednesdays","path":"d3.time","type":"Function","args":["t0","t1","dt"]},{"name":"wednesdayOfYear","path":"d3.time","type":"Function","args":["date"]},{"name":"thursday","path":"d3.time","type":"Function","args":["date"]},{"name":"thursdays","path":"d3.time","type":"Function","args":["t0","t1","dt"]},{"name":"thursdayOfYear","path":"d3.time","type":"Function","args":["date"]},{"name":"friday","path":"d3.time","type":"Function","args":["date"]},{"name":"fridays","path":"d3.time","type":"Function","args":["t0","t1","dt"]},{"name":"fridayOfYear","path":"d3.time","type":"Function","args":["date"]},{"name":"saturday","path":"d3.time","type":"Function","args":["date"]},{"name":"saturdays","path":"d3.time","type":"Function","args":["t0","t1","dt"]},{"name":"saturdayOfYear","path":"d3.time","type":"Function","args":["date"]},{"name":"week","path":"d3.time","type":"Function","args":["date"]},{"name":"weeks","path":"d3.time","type":"Function","args":["t0","t1","dt"]},{"name":"weekOfYear","path":"d3.time","type":"Function","args":["date"]},{"name":"format","path":"d3.time","type":"Function","args":["template"]},{"name":"second","path":"d3.time","type":"Function","args":["date"]},{"name":"seconds","path":"d3.time","type":"Function","args":["t0","t1","dt"]},{"name":"minute","path":"d3.time","type":"Function","args":["date"]},{"name":"minutes","path":"d3.time","type":"Function","args":["t0","t1","dt"]},{"name":"hour","path":"d3.time","type":"Function","args":["date"]},{"name":"hours","path":"d3.time","type":"Function","args":["t0","t1","dt"]},{"name":"month","path":"d3.time","type":"Function","args":["date"]},{"name":"months","path":"d3.time","type":"Function","args":["t0","t1","dt"]},{"name":"scale","path":"d3.time","type":"Function"},{"name":"time","path":"d3","type":"Object"},{"name":"locale","path":"d3","type":"Function","args":["locale"]},{"name":"format","path":"d3","type":"Function","args":["specifier"]},{"name":"stream","path":"d3.geo","type":"Function","args":["object","listener"]},{"name":"area","path":"d3.geo","type":"Function","args":["object"]},{"name":"bounds","path":"d3.geo","type":"Function","args":["feature"]},{"name":"centroid","path":"d3.geo","type":"Function","args":["object"]},{"name":"clipExtent","path":"d3.geo","type":"Function"},{"name":"conicEqualArea","path":"d3.geo","type":"Function"},{"name":"albers","path":"d3.geo","type":"Function"},{"name":"albersUsa","path":"d3.geo","type":"Function"},{"name":"path","path":"d3.geo","type":"Function"},{"name":"transform","path":"d3.geo","type":"Function","args":["methods"]},{"name":"projection","path":"d3.geo","type":"Function","args":["project"]},{"name":"projectionMutator","path":"d3.geo","type":"Function","args":["projectAt"]},{"name":"equirectangular","path":"d3.geo","type":"Function"},{"name":"rotation","path":"d3.geo","type":"Function","args":["rotate"]},{"name":"circle","path":"d3.geo","type":"Function"},{"name":"distance","path":"d3.geo","type":"Function","args":["a","b"]},{"name":"graticule","path":"d3.geo","type":"Function"},{"name":"greatArc","path":"d3.geo","type":"Function"},{"name":"interpolate","path":"d3.geo","type":"Function","args":["source","target"]},{"name":"length","path":"d3.geo","type":"Function","args":["object"]},{"name":"azimuthalEqualArea","path":"d3.geo","type":"Function"},{"name":"azimuthalEquidistant","path":"d3.geo","type":"Function"},{"name":"conicConformal","path":"d3.geo","type":"Function"},{"name":"conicEquidistant","path":"d3.geo","type":"Function"},{"name":"gnomonic","path":"d3.geo","type":"Function"},{"name":"mercator","path":"d3.geo","type":"Function"},{"name":"orthographic","path":"d3.geo","type":"Function"},{"name":"stereographic","path":"d3.geo","type":"Function"},{"name":"transverseMercator","path":"d3.geo","type":"Function"},{"name":"geo","path":"d3","type":"Object"},{"name":"hull","path":"d3.geom","type":"Function","args":["vertices"]},{"name":"polygon","path":"d3.geom","type":"Function","args":["coordinates"]},{"name":"voronoi","path":"d3.geom","type":"Function","args":["points"]},{"name":"delaunay","path":"d3.geom","type":"Function","args":["vertices"]},{"name":"quadtree","path":"d3.geom","type":"Function","args":["points","x1","y1","x2","y2"]},{"name":"geom","path":"d3","type":"Object"},{"name":"interpolateRgb","path":"d3","type":"Function","args":["a","b"]},{"name":"interpolateObject","path":"d3","type":"Function","args":["a","b"]},{"name":"interpolateNumber","path":"d3","type":"Function","args":["a","b"]},{"name":"interpolateString","path":"d3","type":"Function","args":["a","b"]},{"name":"interpolate","path":"d3","type":"Function","args":["a","b"]},{"name":"interpolators","path":"d3","type":"Array"},{"name":"interpolateArray","path":"d3","type":"Function","args":["a","b"]},{"name":"ease","path":"d3","type":"Function","args":["name"]},{"name":"interpolateHcl","path":"d3","type":"Function","args":["a","b"]},{"name":"interpolateHsl","path":"d3","type":"Function","args":["a","b"]},{"name":"interpolateLab","path":"d3","type":"Function","args":["a","b"]},{"name":"interpolateRound","path":"d3","type":"Function","args":["a","b"]},{"name":"transform","path":"d3","type":"Function","args":["string"]},{"name":"interpolateTransform","path":"d3","type":"Function","args":["a","b"]},{"name":"bundle","path":"d3.layout","type":"Function"},{"name":"chord","path":"d3.layout","type":"Function"},{"name":"force","path":"d3.layout","type":"Function"},{"name":"hierarchy","path":"d3.layout","type":"Function"},{"name":"partition","path":"d3.layout","type":"Function"},{"name":"pie","path":"d3.layout","type":"Function"},{"name":"stack","path":"d3.layout","type":"Function"},{"name":"histogram","path":"d3.layout","type":"Function"},{"name":"pack","path":"d3.layout","type":"Function"},{"name":"tree","path":"d3.layout","type":"Function"},{"name":"cluster","path":"d3.layout","type":"Function"},{"name":"treemap","path":"d3.layout","type":"Function"},{"name":"layout","path":"d3","type":"Object"},{"name":"normal","path":"d3.random","type":"Function","args":null},{"name":"logNormal","path":"d3.random","type":"Function"},{"name":"bates","path":"d3.random","type":"Function","args":["m"]},{"name":"irwinHall","path":"d3.random","type":"Function","args":["m"]},{"name":"random","path":"d3","type":"Object"},{"name":"linear","path":"d3.scale","type":"Function"},{"name":"log","path":"d3.scale","type":"Function"},{"name":"pow","path":"d3.scale","type":"Function"},{"name":"sqrt","path":"d3.scale","type":"Function"},{"name":"ordinal","path":"d3.scale","type":"Function"},{"name":"category10","path":"d3.scale","type":"Function"},{"name":"category20","path":"d3.scale","type":"Function"},{"name":"category20b","path":"d3.scale","type":"Function"},{"name":"category20c","path":"d3.scale","type":"Function"},{"name":"quantile","path":"d3.scale","type":"Function"},{"name":"quantize","path":"d3.scale","type":"Function"},{"name":"threshold","path":"d3.scale","type":"Function"},{"name":"identity","path":"d3.scale","type":"Function"},{"name":"scale","path":"d3","type":"Object"},{"name":"arc","path":"d3.svg","type":"Function"},{"name":"line","path":"d3.svg","type":"Function"},{"name":"area","path":"d3.svg","type":"Function"},{"name":"chord","path":"d3.svg","type":"Function"},{"name":"diagonal","path":"d3.svg","type":"Function"},{"name":"symbol","path":"d3.svg","type":"Function"},{"name":"symbolTypes","path":"d3.svg","type":"Array"},{"name":"axis","path":"d3.svg","type":"Function"},{"name":"brush","path":"d3.svg","type":"Function"},{"name":"svg","path":"d3","type":"Object"},{"name":"length","path":"d3.transition","type":"Number"},{"name":"call","path":"d3.transition","type":"Function","args":["callback"]},{"name":"empty","path":"d3.transition","type":"Function"},{"name":"node","path":"d3.transition","type":"Function"},{"name":"size","path":"d3.transition","type":"Function"},{"name":"select","path":"d3.transition","type":"Function","args":["selector"]},{"name":"selectAll","path":"d3.transition","type":"Function","args":["selector"]},{"name":"filter","path":"d3.transition","type":"Function","args":["filter"]},{"name":"tween","path":"d3.transition","type":"Function","args":["name","tween"]},{"name":"attr","path":"d3.transition","type":"Function","args":["nameNS","value"]},{"name":"attrTween","path":"d3.transition","type":"Function","args":["nameNS","tween"]},{"name":"style","path":"d3.transition","type":"Function","args":["name","value","priority"]},{"name":"styleTween","path":"d3.transition","type":"Function","args":["name","tween","priority"]},{"name":"text","path":"d3.transition","type":"Function","args":["value"]},{"name":"remove","path":"d3.transition","type":"Function"},{"name":"ease","path":"d3.transition","type":"Function","args":["value"]},{"name":"delay","path":"d3.transition","type":"Function","args":["value"]},{"name":"duration","path":"d3.transition","type":"Function","args":["value"]},{"name":"each","path":"d3.transition","type":"Function","args":["type","listener"]},{"name":"transition","path":"d3.transition","type":"Function"},{"name":"length","path":"d3.transition","type":"Number"},{"name":"transition","path":"d3","type":"Function","args":["selection","name"]},{"name":"text","path":"d3","type":"Function","args":["url","mimeType","callback"]},{"name":"json","path":"d3","type":"Function","args":["url","callback"]},{"name":"html","path":"d3","type":"Function","args":["url","callback"]},{"name":"xml","path":"d3","type":"Function","args":["url","mimeType","callback"]},{"name":"d3","path":"","type":"Object"}],"hierarchy":{"d3.hsl":"d3.color","d3.hcl":"d3.color","d3.lab":"d3.color","d3.rgb":"d3.color"}}